mercuryclient/__init__.py
mercuryclient/api.py
mercuryclient/http_utils.py
mercuryclient/mixins/__init__.py
mercuryclient/mixins/auth.py
mercuryclient/mixins/bank_account_verify.py
mercuryclient/mixins/bank_statement.py
mercuryclient/mixins/bbps.py
mercuryclient/mixins/cibil.py
mercuryclient/mixins/ckyc.py
mercuryclient/mixins/e_sign_verification.py
mercuryclient/mixins/epfo_verification.py
mercuryclient/mixins/equifax.py
mercuryclient/mixins/experian.py
mercuryclient/mixins/gst_verificaion.py
mercuryclient/mixins/highmark.py
mercuryclient/mixins/id_verification.py
mercuryclient/mixins/insurance.py
mercuryclient/mixins/itr_extraction.py
mercuryclient/mixins/itr_pull.py
mercuryclient/mixins/mail.py
mercuryclient/mixins/name_matching.py
mercuryclient/mixins/okyc_verification.py
mercuryclient/mixins/payments.py
mercuryclient/mixins/rc_verification.py
mercuryclient/mixins/recharge.py
mercuryclient/mixins/rekognition.py
mercuryclient/mixins/sms.py
mercuryclient/mixins/udyog_aadhaar_verify.py
mercuryclient/mixins/utilities_verification.py
mercuryclient/mixins/webhooks.py
mercuryclient/mixins/tests/__init__.py
mercuryclient/mixins/tests/test_auth.py
mercuryclient/mixins/tests/test_bank_account_verify.py
mercuryclient/mixins/tests/test_bank_statement.py
mercuryclient/mixins/tests/test_bbps.py
mercuryclient/mixins/tests/test_cibil.py
mercuryclient/mixins/tests/test_ckyc.py
mercuryclient/mixins/tests/test_e_sign_counter.py
mercuryclient/mixins/tests/test_epfo.py
mercuryclient/mixins/tests/test_equifax.py
mercuryclient/mixins/tests/test_experian.py
mercuryclient/mixins/tests/test_gst_verification.py
mercuryclient/mixins/tests/test_highmark.py
mercuryclient/mixins/tests/test_id_verification.py
mercuryclient/mixins/tests/test_insurance.py
mercuryclient/mixins/tests/test_itr_extraction.py
mercuryclient/mixins/tests/test_itr_pull.py
mercuryclient/mixins/tests/test_name_matching.py
mercuryclient/mixins/tests/test_okyc_verification.py
mercuryclient/mixins/tests/test_payments.py
mercuryclient-1.23.1.dist-info/METADATA
mercuryclient-1.23.1.dist-info/WHEEL
mercuryclient-1.23.1.dist-info/top_level.txt
mercuryclient-1.23.1.dist-info/RECORD
