Metadata-Version: 2.1
Name: mercuryclient
Version: 1.23.1
Summary: Python SDK for Mercury service
Home-page: https://bitbucket.org/esthenos/mercury
Author: Esthenos Technologies Private Limited
Author-email: atul@esthenos.com 
License: Proprietary License
Platform: UNKNOWN
Requires-Python: >=3.6
Requires-Dist: requests (<3,>=2.25.0)
Requires-Dist: PyJWT (<2,>=1.7.0)
Requires-Dist: pydantic (<2,>=1.7.0)
Requires-Dist: PyPDF2 (<3,>=1.26.0)
Provides-Extra: dev
Requires-Dist: pre-commit ; extra == 'dev'
Requires-Dist: wheel ; extra == 'dev'
Requires-Dist: twine ; extra == 'dev'
